todo/__init__.py
todo/__main__.py
todo/_version.py
todo/commands/__init__.py
todo/commands/add.py
todo/commands/auto.py
todo/commands/base.py
todo/commands/delete.py
todo/commands/done.py
todo/commands/list.py
todo/commands/setup.py
todo/commands/update.py
todo/database/__init__.py
todo/database/database.py
todo/database/drivers/__init__.py
todo/database/drivers/base.py
todo/database/drivers/file/__init__.py
todo/database/drivers/file/file.py
todo/database/drivers/file/versions.py
todo/types/__init__.py
todo/types/config.py
todo/types/task.py
venv/bin/activate_this.py
todotui-0.0.4.dist-info/LICENSE
todotui-0.0.4.dist-info/METADATA
todotui-0.0.4.dist-info/WHEEL
todotui-0.0.4.dist-info/entry_points.txt
todotui-0.0.4.dist-info/top_level.txt
todotui-0.0.4.dist-info/RECORD
