Metadata-Version: 2.2
Name: todotui
Version: 0.0.4
Summary: Tui for managing todo lists
Author-email: Tobias Persson <tobias.persson@tp-softworks.se>
License: MIT
License-File: LICENSE
Requires-Dist: docopt==0.6.2
Requires-Dist: pyyaml==6.0.2
Requires-Dist: pydantic==2.10.6
